QGFD_Sanity_Checks.py
qgfd_attention.py
universal_qgfd_replacer.py
Dire/__init__.py
Distributed/__init__.py
layers/BrainFindingsExtractor.py
layers/qgfd.py
torchdire-1.0.0.dist-info/licenses/LICENSE
torchdire-1.0.0.dist-info/METADATA
torchdire-1.0.0.dist-info/WHEEL
torchdire-1.0.0.dist-info/top_level.txt
torchdire-1.0.0.dist-info/RECORD
