Metadata-Version: 2.4
Name: torchdire
Version: 1.0.0
Summary: Library for simplified AI model building with QGFD and YAML-based automation.
Home-page: https://github.com/rajboopathiking/TorchDire
Author: Boopathi Raj
Author-email: Boopathi Raj <rajboopathiking@gmail.com>
License: MIT License
Keywords: pytorch,deep learning,qgfd,robustness,automation,yaml,ml,ai
Classifier: Programming Language :: Python :: 3
Classifier: Programming Language :: Python :: 3.9
Classifier: Programming Language :: Python :: 3.10
Classifier: Programming Language :: Python :: 3.11
Classifier: License :: OSI Approved :: MIT License
Classifier: Operating System :: OS Independent
Classifier: Topic :: Scientific/Engineering :: Artificial Intelligence
Requires-Python: >=3.8
License-File: LICENSE
Requires-Dist: torch<2.3.0,>=2.0.0
Requires-Dist: torchvision>=0.15.0
Requires-Dist: timm
Requires-Dist: PyYAML>=6.0
Requires-Dist: tqdm
Requires-Dist: numpy<2
Requires-Dist: matplotlib
Requires-Dist: seaborn
Requires-Dist: pandas
Requires-Dist: onnx
Requires-Dist: onnxruntime
Requires-Dist: onnxruntime-tools
Provides-Extra: dev
Requires-Dist: pytest; extra == "dev"
Requires-Dist: pytest-cov; extra == "dev"
Requires-Dist: flake8; extra == "dev"
Requires-Dist: mypy; extra == "dev"
Requires-Dist: black; extra == "dev"
Dynamic: author
Dynamic: home-page
Dynamic: license-file
Dynamic: requires-python
